AOI_API/__init__.py
AOI_API/api_client.py
AOI_API/configuration.py
AOI_API/exceptions.py
AOI_API/rest.py
AOI_API/api/__init__.py
AOI_API/api/aoi_api.py
AOI_API/models/__init__.py
AOI_API/models/db_phrame_json_store.py
aoi_package-2.0.2.dist-info/licenses/LICENSE
aoi_package-2.0.2.dist-info/METADATA
aoi_package-2.0.2.dist-info/WHEEL
aoi_package-2.0.2.dist-info/top_level.txt
aoi_package-2.0.2.dist-info/RECORD
