Metadata-Version: 2.4
Name: AOI-Package
Version: 2.0.2
Summary: AOI API
Home-page: 
Author: Corey Sadler
Author-email: Corey Sadler <corey.sadler@3adesign.co.uk>
License: Copyright © 2023 3ADesign Limited
Keywords: OpenAPI,OpenAPI-Generator,AOI API
Classifier: License :: OSI Approved :: MIT License
Classifier: Programming Language :: Python
Classifier: Programming Language :: Python :: 3
Requires-Python: >=3.4
License-File: LICENSE
Requires-Dist: connexion>=2.0.2
Requires-Dist: swagger-ui-bundle>=0.0.2
Requires-Dist: python_dateutil>=2.6.0
Requires-Dist: setuptools>=21.0.0
Requires-Dist: requests
Dynamic: author
Dynamic: license-file
